Metadata-Version: 1.1
Name: mapykoB
Version: 0.0.3
Summary: Package for sequence modeling with Andrei Markov's models
Home-page: https://github.com/octoandzl/mapykoB
Author: Andzl
Author-email: andzlhub@gmail.com
License: MIT
Platform: UNKNOWN
Classifier: Development Status :: 3 - Alpha
Classifier: License :: OSI Approved :: MIT License
Classifier: Programming Language :: Python :: 3.5
Classifier: Programming Language :: Python :: Implementation :: CPython
Classifier: Programming Language :: Python :: Implementation :: PyPy
